{
  "status": "ready",
  "progress": 1,
  "total_chunks": 1,
  "source_language": "English (με ένα γαλλικό απόφθεγμα στην αρχή)",
  "document_brief": "Τύπος: Λογοτεχνικό (Εναλλακτική ιστορία / Τρόμου / Weird Fiction)\nΘέμα: Η αφήγηση ενός ψυχολογικά ασταθούς άνδρα σε μια εναλλακτική Αμερική του 1920, ο οποίος περιγράφει τις κοινωνικές αλλαγές, τα εγκαίνια ενός κυβερνητικού θαλάμου αυτοκτονίας και την εμμονή του με το καταραμένο βιβλίο «Ο Βασιλιάς με τα Κίτρινα».\nΕποχή/Πλαίσιο: Γράφτηκε το 1895 (απόσπασμα από το διήγημα 'The Repairer of Reputations' του Robert W. Chambers) και διαδραματίζεται σε ένα φανταστικό, μελλοντικό για την εποχή συγγραφής 1920.\nΎφος: Λογοτεχνικό, επίσημο, με εναλλαγές μεταξύ ψυχρής, σχεδόν δημοσιογραφικής ιστορικής καταγραφής και παραληρηματικής, συναισθηματικά φορτισμένης αφήγησης (αναξιόπιστος αφηγητής).\nΣημειώσεις: Το κείμενο ξεκινά με ένα γαλλικό απόφθεγμα το οποίο συνήθως διατηρείται στο πρωτότυπο με ελληνική μετάφραση σε υποσημείωση. Η μεγαλύτερη πρόκληση είναι η απόδοση του ύφους του αναξιόπιστου αφηγητή: η μετάβαση από την ψυχρή περιγραφή της εναλλακτικής ιστορίας της Αμερικής, στον απόλυτο τρόμο και την εμμονή όταν αναφέρεται στο βιβλίο. Προσοχή στην απόδοση των στρατιωτικών και κυβερνητικών βαθμών/τίτλων (π.χ. Inspector-General of Police, Surgeon-General) ώστε να ταιριάζουν στο αμερικανικό σύστημα αλλά να είναι φυσικοί στα ελληνικά. Επίσης, η λέξη 'negro' στο πλαίσιο της εποχής (1895) μεταφράζεται συνήθως ως 'νέγρικος' ή 'των μαύρων' ανάλογα με τις κατευθυντήριες γραμμές του εκδότη για ιστορικά κείμενα.",
  "glossary": [
    {
      "source": "The King in Yellow",
      "target": "Ο Βασιλιάς με τα Κίτρινα",
      "note": "Καθιερωμένη απόδοση του τίτλου του βιβλίου/θεατρικού έργου."
    },
    {
      "source": "Government Lethal Chamber",
      "target": "Κυβερνητικός Θάλαμος Θανάτου / Κυβερνητικός Θάλαμος Ευθανασίας",
      "note": "Απαιτείται ένας όρος που να ακούγεται γραφειοκρατικός αλλά και μακάβριος."
    },
    {
      "source": "Pallid Mask",
      "target": "Ωχρή Μάσκα",
      "note": "Σημαντικό σύμβολο της μυθολογίας του έργου."
    },
    {
      "source": "Armourer",
      "target": "Οπλοποιός / Κατασκευαστής πανοπλιών",
      "note": "Αναφέρεται στο επάγγελμα του Hawberk στην επιγραφή του καταστήματος."
    },
    {
      "source": "President Winthrop",
      "target": "Πρόεδρος Γουίνθροπ",
      "note": "person"
    },
    {
      "source": "General Von Gartenlaube",
      "target": "Στρατηγός Φον Γκαρτενλάουμπε",
      "note": "person"
    },
    {
      "source": "Dr. Archer",
      "target": "Δρ. Άρτσερ",
      "note": "person"
    },
    {
      "source": "Boris Yvain",
      "target": "Μπόρις Ιβάν",
      "note": "person"
    },
    {
      "source": "Colonel Livingston",
      "target": "Συνταγματάρχης Λίβινγκστον",
      "note": "person"
    },
    {
      "source": "General Blount",
      "target": "Στρατηγός Μπλάουντ",
      "note": "person"
    },
    {
      "source": "Major-General Hamilton",
      "target": "Υποστράτηγος Χάμιλτον",
      "note": "person"
    },
    {
      "source": "Admiral Buffby",
      "target": "Ναύαρχος Μπάφμπι",
      "note": "person"
    },
    {
      "source": "Surgeon-General Lanceford",
      "target": "Γενικός Χειρουργός Λάνσφορντ",
      "note": "person"
    },
    {
      "source": "Senator Wyse",
      "target": "Γερουσιαστής Γουάις",
      "note": "person"
    },
    {
      "source": "Senator Franklin",
      "target": "Γερουσιαστής Φράνκλιν",
      "note": "person"
    },
    {
      "source": "Hawberk",
      "target": "Χόμπερκ",
      "note": "person"
    },
    {
      "source": "United States",
      "target": "Ηνωμένες Πολιτείες",
      "note": "place"
    },
    {
      "source": "Germany",
      "target": "Γερμανία",
      "note": "place"
    },
    {
      "source": "Samoan Islands",
      "target": "Νησιά Σαμόα",
      "note": "place"
    },
    {
      "source": "Norfolk",
      "target": "Νόρφολκ",
      "note": "place"
    },
    {
      "source": "State of New Jersey",
      "target": "Πολιτεία του Νιου Τζέρσεϊ",
      "note": "place"
    },
    {
      "source": "Cuba",
      "target": "Κούβα",
      "note": "place"
    },
    {
      "source": "Hawaii",
      "target": "Χαβάη",
      "note": "place"
    },
    {
      "source": "Samoa",
      "target": "Σαμόα",
      "note": "place"
    },
    {
      "source": "West",
      "target": "Δύση",
      "note": "place"
    },
    {
      "source": "Chicago",
      "target": "Σικάγο",
      "note": "place"
    },
    {
      "source": "New York",
      "target": "Νέα Υόρκη",
      "note": "place"
    },
    {
      "source": "France",
      "target": "Γαλλία",
      "note": "place"
    },
    {
      "source": "England",
      "target": "Αγγλία",
      "note": "place"
    },
    {
      "source": "Suanee",
      "target": "Σουάνι",
      "note": "place"
    },
    {
      "source": "Italy",
      "target": "Ιταλία",
      "note": "place"
    },
    {
      "source": "Spain",
      "target": "Ισπανία",
      "note": "place"
    },
    {
      "source": "Belgium",
      "target": "Βέλγιο",
      "note": "place"
    },
    {
      "source": "Russia",
      "target": "Ρωσία",
      "note": "place"
    },
    {
      "source": "Caucasus",
      "target": "Καύκασος",
      "note": "place"
    },
    {
      "source": "Washington Square",
      "target": "Πλατεία Ουάσινγκτον",
      "note": "place"
    },
    {
      "source": "Madison Avenue",
      "target": "Λεωφόρος Μάντισον",
      "note": "place"
    },
    {
      "source": "Carcosa",
      "target": "Καρκόσα",
      "note": "place"
    },
    {
      "source": "lake of Hali",
      "target": "Λίμνη του Χάλι",
      "note": "place"
    },
    {
      "source": "Paris",
      "target": "Παρίσι",
      "note": "place"
    },
    {
      "source": "London",
      "target": "Λονδίνο",
      "note": "place"
    },
    {
      "source": "Wooster Street",
      "target": "Οδός Γούστερ",
      "note": "place"
    },
    {
      "source": "South Fifth Avenue",
      "target": "Νότια Πέμπτη Λεωφόρος",
      "note": "place"
    },
    {
      "source": "University Place",
      "target": "Γιουνιβέρσιτι Πλέις",
      "note": "place"
    },
    {
      "source": "Fourth Street",
      "target": "Τέταρτη Οδός",
      "note": "place"
    },
    {
      "source": "Washington Park",
      "target": "Πάρκο Ουάσινγκτον",
      "note": "place"
    },
    {
      "source": "Brooklyn",
      "target": "Μπρούκλιν",
      "note": "place"
    },
    {
      "source": "Governor’s Island",
      "target": "Νησί του Κυβερνήτη",
      "note": "place"
    },
    {
      "source": "North River",
      "target": "Βόρειος Ποταμός",
      "note": "place"
    },
    {
      "source": "Fifth Avenue",
      "target": "Πέμπτη Λεωφόρος",
      "note": "place"
    },
    {
      "source": "Bleecker Street",
      "target": "Οδός Μπλίκερ",
      "note": "place"
    },
    {
      "source": "Government of the United States",
      "target": "Κυβέρνηση των Ηνωμένων Πολιτειών",
      "note": "org"
    },
    {
      "source": "General Staff",
      "target": "Γενικό Επιτελείο",
      "note": "org"
    },
    {
      "source": "United States National Academy of Design",
      "target": "Εθνική Ακαδημία Σχεδίου των Ηνωμένων Πολιτειών",
      "note": "org"
    },
    {
      "source": "National Mounted Police",
      "target": "Εθνική Έφιππη Αστυνομία",
      "note": "org"
    },
    {
      "source": "Congress of Religions",
      "target": "Συνέδριο των Θρησκειών",
      "note": "org"
    },
    {
      "source": "National Free Hospital",
      "target": "Εθνικό Δωρεάν Νοσοκομείο",
      "note": "org"
    },
    {
      "source": "National Guard",
      "target": "Εθνοφρουρά",
      "note": "org"
    },
    {
      "source": "Fates",
      "target": "Μοίρες",
      "note": "title"
    },
    {
      "source": "Dodge Statue",
      "target": "Άγαλμα του Ντοτζ",
      "note": "title"
    },
    {
      "source": "Lethal Chamber",
      "target": "Θάλαμος Θανάτου",
      "note": "term"
    },
    {
      "source": "Elevated Railroads",
      "target": "Υπέργειοι Σιδηρόδρομοι",
      "note": "term"
    },
    {
      "source": "suicide",
      "target": "αυτοκτονία",
      "note": "term"
    },
    {
      "source": "squadron",
      "target": "ίλη / μοίρα",
      "note": "term"
    },
    {
      "source": "lancers",
      "target": "λογχοφόροι",
      "note": "term"
    },
    {
      "source": "hussars",
      "target": "ουσάροι",
      "note": "term"
    },
    {
      "source": "garrison",
      "target": "φρουρά",
      "note": "term"
    },
    {
      "source": "commandant",
      "target": "διοικητής",
      "note": "term"
    },
    {
      "source": "military aid",
      "target": "στρατιωτικός ακόλουθος",
      "note": "term"
    },
    {
      "source": "Surgeon-General",
      "target": "Γενικός Χειρουργός",
      "note": "term"
    },
    {
      "source": "self-destruction",
      "target": "αυτοκαταστροφή",
      "note": "term"
    },
    {
      "source": "self-preservation",
      "target": "αυτοσυντήρηση",
      "note": "term"
    },
    {
      "source": "cavalry",
      "target": "ιππικό",
      "note": "term"
    },
    {
      "source": "architecture",
      "target": "αρχιτεκτονική",
      "note": "term"
    },
    {
      "source": "Secretary of Fine Arts",
      "target": "Υπουργός Καλών Τεχνών",
      "note": "term"
    },
    {
      "source": "Secretary of Forestry and Game Preservation",
      "target": "Υπουργός Δασών και Προστασίας Θηραμάτων",
      "note": "term"
    },
    {
      "source": "Secretary of War",
      "target": "Υπουργός Πολέμου",
      "note": "term"
    },
    {
      "source": "Inspector-General of Police",
      "target": "Γενικός Επιθεωρητής Αστυνομίας",
      "note": "term"
    },
    {
      "source": "Commissioner of Public Works",
      "target": "Επίτροπος Δημοσίων Έργων",
      "note": "term"
    }
  ],
  "translated": [
    "«Ne raillons pas les fous; leur folie dure plus longtemps que la nôtre.... Voila toute la différence.» [«Ας μην περιγελάμε τους τρελούς· η τρέλα τους διαρκεί περισσότερο από τη δική μας... Αυτή είναι όλη η διαφορά.»]",
    "Προς τα τέλη του έτους 1920, η Κυβέρνηση των Ηνωμένων Πολιτειών είχε σχεδόν ολοκληρώσει το πρόγραμμα που είχε υιοθετηθεί κατά τους τελευταίους μήνες της διακυβέρνησης του Προέδρου Γουίνθροπ. Η χώρα ήταν φαινομενικά γαλήνια. Όλοι γνωρίζουν πώς διευθετήθηκαν τα ζητήματα των Δασμών και της Εργασίας. Ο πόλεμος με τη Γερμανία, που προκλήθηκε από την κατάληψη των Νησιών Σαμόα από τη χώρα αυτή, δεν είχε αφήσει ορατά σημάδια στη δημοκρατία, και η προσωρινή κατοχή του Νόρφολκ από τον στρατό εισβολής είχε ξεχαστεί μέσα στη χαρά για τις αλλεπάλληλες ναυτικές νίκες και την επακόλουθη γελοία κατάσταση των δυνάμεων του Στρατηγού Φον Γκαρτενλάουμπε στην Πολιτεία του Νιου Τζέρσεϊ. Οι επενδύσεις στην Κούβα και τη Χαβάη είχαν αποδώσει εκατό τοις εκατό και η επικράτεια της Σαμόα άξιζε και με το παραπάνω το κόστος της ως σταθμός ανεφοδιασμού άνθρακα. Η χώρα βρισκόταν σε εξαιρετική αμυντική κατάσταση. Κάθε παράκτια πόλη είχε εξοπλιστεί επαρκώς με χερσαίες οχυρώσεις· ο στρατός, υπό το πατρικό βλέμμα του Γενικού Επιτελείου, οργανωμένος σύμφωνα με το πρωσικό σύστημα, είχε αυξηθεί σε 300.000 άνδρες, με τοπική εφεδρεία ενός εκατομμυρίου· και έξι υπέροχες Μοίρες καταδρομικών και θωρηκτών περιπολούσαν τους έξι σταθμούς των πλεύσιμων θαλασσών, αφήνοντας μια ατμοκίνητη εφεδρεία απολύτως ικανή να ελέγχει τα εγχώρια ύδατα. Οι κύριοι από τη Δύση είχαν επιτέλους αναγκαστεί να αναγνωρίσουν ότι ένα κολέγιο για την εκπαίδευση διπλωματών ήταν εξίσου απαραίτητο με τις νομικές σχολές για την εκπαίδευση των δικηγόρων· κατά συνέπεια, δεν εκπροσωπούμασταν πλέον στο εξωτερικό από ανίκανους πατριώτες. Το έθνος ευημερούσε· το Σικάγο, παραλυμένο για μια στιγμή μετά από μια δεύτερη μεγάλη πυρκαγιά, είχε αναδυθεί από τα ερείπιά του, λευκό και αυτοκρατορικό, και πιο όμορφο από τη λευκή πόλη που είχε χτιστεί για να αποτελέσει το παιχνίδι του το 1893. Παντού η καλή αρχιτεκτονική αντικαθιστούσε την κακή, και ακόμη και στη Νέα Υόρκη, μια ξαφνική λαχτάρα για ευπρέπεια είχε σαρώσει ένα μεγάλο μέρος των υφιστάμενων τερατουργημάτων. Οι δρόμοι είχαν διαπλατυνθεί, είχαν στρωθεί και φωτιστεί σωστά, δέντρα είχαν φυτευτεί, πλατείες είχαν διαμορφωθεί, υπερυψωμένες κατασκευές είχαν κατεδαφιστεί και υπόγειοι δρόμοι είχαν κατασκευαστεί για να τις αντικαταστήσουν. Τα νέα κυβερνητικά κτίρια και οι στρατώνες αποτελούσαν εξαιρετικά δείγματα αρχιτεκτονικής, και το μακρύ σύστημα πέτρινων αποβαθρών που περιέβαλλε πλήρως το νησί είχε μετατραπεί σε πάρκα που αποδείχθηκαν θείο δώρο για τον πληθυσμό. Η επιδότηση του κρατικού θεάτρου και της κρατικής όπερας είχε τη δική της ανταμοιβή. Η Εθνική Ακαδημία Σχεδίου των Ηνωμένων Πολιτειών έμοιαζε πολύ με τα ευρωπαϊκά ιδρύματα του ίδιου είδους. Κανείς δεν ζήλευε τον Υπουργό Καλών Τεχνών, ούτε τη θέση του στο υπουργικό συμβούλιο ούτε το χαρτοφυλάκιό του. Ο Υπουργός Δασών και Προστασίας Θηραμάτων είχε πολύ πιο εύκολο έργο, χάρη στο νέο σύστημα της Εθνικής Έφιππης Αστυνομίας. Είχαμε επωφεληθεί τα μέγιστα από τις πρόσφατες συνθήκες με τη Γαλλία και την Αγγλία· ο αποκλεισμός των αλλοδαπών Εβραίων ως μέτρο αυτοσυντήρησης, η εγκαθίδρυση του νέου ανεξάρτητου νέγρικου κράτους του Σουάνι, ο έλεγχος της μετανάστευσης, οι νέοι νόμοι περί πολιτογράφησης και η σταδιακή συγκέντρωση της εξουσίας στα χέρια της εκτελεστικής βαθμίδας συνέβαλαν όλα στην εθνική ηρεμία και ευημερία. Όταν η Κυβέρνηση έλυσε το ινδιάνικο πρόβλημα και ίλες Ινδιάνων ανιχνευτών ιππικού με παραδοσιακές ενδυμασίες αντικατέστησαν τους αξιολύπητους σχηματισμούς που είχε προσκολλήσει στην ουρά αποσκελετωμένων συνταγμάτων ένας πρώην Υπουργός Πολέμου, το έθνος ανέπνευσε με ανακούφιση. Όταν, μετά το κολοσσιαίο Συνέδριο των Θρησκειών, ο φανατισμός και η μισαλλοδοξία ενταφιάστηκαν και η καλοσύνη και η φιλανθρωπία άρχισαν να φέρνουν κοντά τις αντιμαχόμενες αιρέσεις, πολλοί πίστεψαν ότι είχε φτάσει η Χιλιετία, τουλάχιστον στον νέο κόσμο, ο οποίος, άλλωστε, αποτελεί έναν κόσμο από μόνος του.",
    "Όμως η αυτοσυντήρηση είναι ο πρώτος νόμος, και οι Ηνωμένες Πολιτείες αναγκάστηκαν να παρακολουθούν με ανήμπορη θλίψη τη Γερμανία, την Ιταλία, την Ισπανία και το Βέλγιο να σφαδάζουν στις οδύνες της Αναρχίας, ενώ η Ρωσία, παραμονεύοντας από τον Καύκασο, έσκυβε και τις έδενε χειροπόδαρα μία προς μία.",
    "Στην πόλη της Νέας Υόρκης, το καλοκαίρι του 1899 σηματοδοτήθηκε από την αποξήλωση των Υπέργειων Σιδηροδρόμων. Το καλοκαίρι του 1900 θα ζει στις μνήμες των κατοίκων της Νέας Υόρκης για πολλές γενιές· το Άγαλμα του Ντοτζ απομακρύνθηκε εκείνη τη χρονιά. Τον επόμενο χειμώνα ξεκίνησε εκείνη η κινητοποίηση για την κατάργηση των νόμων που απαγόρευαν την αυτοκτονία, η οποία απέδωσε τους τελικούς της καρπούς τον μήνα Απρίλιο του 1920, όταν άνοιξε ο πρώτος Κυβερνητικός Θάλαμος Θανάτου στην Πλατεία Ουάσινγκτον.",
    "Εκείνη την ημέρα είχα κατηφορίσει από το σπίτι του Δρ. Άρτσερ στη Λεωφόρο Μάντισον, όπου είχα πάει καθαρά για τυπικούς λόγους. Από τότε που έπεσα από το άλογό μου, τέσσερα χρόνια πριν, με ταλαιπωρούσαν κατά καιρούς πόνοι στο πίσω μέρος του κεφαλιού και στον αυχένα μου, αλλά πλέον απουσίαζαν εδώ και μήνες, και ο γιατρός με έδιωξε εκείνη την ημέρα λέγοντας ότι δεν υπήρχε τίποτα άλλο να θεραπεύσει πάνω μου. Δύσκολα δικαιολογούσε την αμοιβή του για να μου πει κάτι τέτοιο· το γνώριζα κι ο ίδιος. Παρόλα αυτά, δεν λυπήθηκα τα χρήματα. Αυτό που με ενοχλούσε ήταν το λάθος που είχε κάνει στην αρχή. Όταν με μάζεψαν από το λιθόστρωτο όπου κειτόμουν αναίσθητος, και κάποιος είχε ρίξει με ευσπλαχνία μια σφαίρα στο κεφάλι του αλόγου μου, με μετέφεραν στον Δρ. Άρτσερ, και εκείνος, αποφαινόμενος ότι ο εγκέφαλός μου είχε υποστεί βλάβη, με έκλεισε στο ιδιωτικό του άσυλο, όπου αναγκάστηκα να υποστώ θεραπεία για παραφροσύνη. Επιτέλους αποφάσισε ότι ήμουν καλά, και εγώ, γνωρίζοντας ότι το μυαλό μου ήταν πάντα εξίσου σώο με το δικό του, αν όχι πιο σώο, «πλήρωσα τα δίδακτρά μου», όπως το αποκαλούσε αστειευόμενος, και έφυγα. Του είπα, χαμογελώντας, ότι θα του το ανταπέδιδα για το λάθος του, και εκείνος γέλασε εγκάρδια, και μου ζήτησε να τον επισκέπτομαι πού και πού. Το έκανα, ελπίζοντας σε μια ευκαιρία να ξεκαθαρίσουμε τους λογαριασμούς μας, αλλά δεν μου έδωσε",
    "",
    "",
    "",
    "",
    "",
    "",
    ""
  ],
  "filename": "test_ Ne raillons pas les fous.docx",
  "is_docx": true,
  "error_message": ""
}